odoo/addons/contract_analytic_tag/README.rst
odoo/addons/contract_analytic_tag/__init__.py
odoo/addons/contract_analytic_tag/__manifest__.py
odoo/addons/contract_analytic_tag/i18n/contract_analytic_tag.pot
odoo/addons/contract_analytic_tag/i18n/es.po
odoo/addons/contract_analytic_tag/i18n/fr.po
odoo/addons/contract_analytic_tag/i18n/it.po
odoo/addons/contract_analytic_tag/models/__init__.py
odoo/addons/contract_analytic_tag/models/contract_line.py
odoo/addons/contract_analytic_tag/readme/CONTRIBUTORS.md
odoo/addons/contract_analytic_tag/readme/DESCRIPTION.md
odoo/addons/contract_analytic_tag/static/description/icon.png
odoo/addons/contract_analytic_tag/static/description/index.html
odoo/addons/contract_analytic_tag/tests/__init__.py
odoo/addons/contract_analytic_tag/tests/test_contract_analytic_tag.py
odoo/addons/contract_analytic_tag/views/contract_line_views.xml
odoo/addons/contract_analytic_tag/views/contract_views.xml
odoo_addon_contract_analytic_tag-18.0.1.0.0.4.dist-info/METADATA
odoo_addon_contract_analytic_tag-18.0.1.0.0.4.dist-info/WHEEL
odoo_addon_contract_analytic_tag-18.0.1.0.0.4.dist-info/top_level.txt
odoo_addon_contract_analytic_tag-18.0.1.0.0.4.dist-info/RECORD
